pylunar/__init__.py
pylunar/altitude_dict.py
pylunar/helpers.py
pylunar/lunar_feature.py
pylunar/lunar_feature_container.py
pylunar/moon_info.py
pylunar/pkg_types.py
pylunar/py.typed
pylunar/data/lunar.db
pylunar-0.11.0.dist-info/licenses/AUTHORS.rst
pylunar-0.11.0.dist-info/licenses/LICENSE
pylunar-0.11.0.dist-info/METADATA
pylunar-0.11.0.dist-info/WHEEL
pylunar-0.11.0.dist-info/top_level.txt
pylunar-0.11.0.dist-info/RECORD
