Metadata-Version: 2.4
Name: pylunar
Version: 0.11.0
Summary: Information for completing the Astronomical League's Lunar and Lunar II observing programs.
Author-email: Michael Reuter <mareuternh@gmail.com>
License-Expression: BSD-3-Clause
Project-URL: Documentation, http://pylunar.readthedocs.io
Project-URL: Repository, https://github.com/mareuter/pylunar
Classifier: Development Status :: 4 - Beta
Classifier: Intended Audience :: Developers
Classifier: Natural Language :: English
Classifier: Programming Language :: Python :: 3
Classifier: Programming Language :: Python :: 3.10
Classifier: Programming Language :: Python :: 3.11
Classifier: Programming Language :: Python :: 3.12
Classifier: Programming Language :: Python :: 3.13
Classifier: Programming Language :: Python :: 3.14
Requires-Python: >=3.10
License-File: LICENSE
License-File: AUTHORS.rst
Requires-Dist: ephem==4.2
Provides-Extra: dev
Requires-Dist: pylunar[build,docs,lint,test]; extra == "dev"
Requires-Dist: scriv==1.8.0; extra == "dev"
Requires-Dist: tox==4.34.1; extra == "dev"
Provides-Extra: test
Requires-Dist: coverage[toml]==7.13.1; extra == "test"
Requires-Dist: pytest==9.0.2; extra == "test"
Provides-Extra: lint
Requires-Dist: pre-commit==4.5.1; extra == "lint"
Provides-Extra: build
Requires-Dist: build==1.4.0; extra == "build"
Requires-Dist: twine==6.2.0; extra == "build"
Provides-Extra: docs
Requires-Dist: sphinx~=7.4; python_version < "3.11" and extra == "docs"
Requires-Dist: sphinx~=8.2; python_version >= "3.11" and extra == "docs"
Requires-Dist: sphinx_rtd_theme==3.1.0; extra == "docs"
Dynamic: license-file
